airbyte/__init__.py
airbyte/connections.py
airbyte/destinations.py
airbyte/jobs.py
airbyte/sdk.py
airbyte/sdkconfiguration.py
airbyte/sources.py
airbyte/streams.py
airbyte/workspaces.py
airbyte/models/__init__.py
airbyte/models/errors/__init__.py
airbyte/models/errors/sdkerror.py
airbyte/models/operations/__init__.py
airbyte/models/operations/canceljob.py
airbyte/models/operations/createconnection.py
airbyte/models/operations/createdestination.py
airbyte/models/operations/createjob.py
airbyte/models/operations/createorupdateworkspaceoauthcredentials.py
airbyte/models/operations/createsource.py
airbyte/models/operations/createworkspace.py
airbyte/models/operations/deleteconnection.py
airbyte/models/operations/deletedestination.py
airbyte/models/operations/deletesource.py
airbyte/models/operations/deleteworkspace.py
airbyte/models/operations/getconnection.py
airbyte/models/operations/getdestination.py
airbyte/models/operations/getjob.py
airbyte/models/operations/getsource.py
airbyte/models/operations/getstreamproperties.py
airbyte/models/operations/getworkspace.py
airbyte/models/operations/initiateoauth.py
airbyte/models/operations/listconnections.py
airbyte/models/operations/listdestinations.py
airbyte/models/operations/listjobs.py
airbyte/models/operations/listsources.py
airbyte/models/operations/listworkspaces.py
airbyte/models/operations/patchconnection.py
airbyte/models/operations/patchdestination.py
airbyte/models/operations/patchsource.py
airbyte/models/operations/putdestination.py
airbyte/models/operations/putsource.py
airbyte/models/operations/updateworkspace.py
airbyte/models/shared/__init__.py
airbyte/models/shared/actortypeenum.py
airbyte/models/shared/airtable.py
airbyte/models/shared/amazon_ads.py
airbyte/models/shared/amazon_seller_partner.py
airbyte/models/shared/asana.py
airbyte/models/shared/bing_ads.py
airbyte/models/shared/connectioncreaterequest.py
airbyte/models/shared/connectionpatchrequest.py
airbyte/models/shared/connectionresponse.py
airbyte-6.0.1.dist-info/LICENSE.md
airbyte-6.0.1.dist-info/METADATA
airbyte-6.0.1.dist-info/WHEEL
airbyte-6.0.1.dist-info/top_level.txt
airbyte-6.0.1.dist-info/RECORD
